LICENSE
README.md
setup.py
quant_matmul/__init__.py
quant_matmul/moe_interface.py
quant_matmul/quant_matmul_interface.py
quant_matmul/quantize.py
quant_matmul.egg-info/PKG-INFO
quant_matmul.egg-info/SOURCES.txt
quant_matmul.egg-info/dependency_links.txt
quant_matmul.egg-info/requires.txt
quant_matmul.egg-info/top_level.txt